BoydCut/__init__.py
BoydCut/utility.py
BoydCut/model/boydcut_model/saved_model.pb
BoydCut/model/boydcut_model/assets/mockup
BoydCut/model/boydcut_model/variables/variables.data-00000-of-00002
BoydCut/model/boydcut_model/variables/variables.data-00001-of-00002
BoydCut/model/boydcut_model/variables/variables.index
BoydCut/utility_data/longtext_v1
BoydCut/utility_data/longtext_v2
BoydCut/utility_data/pos_idx_dict.pkl
BoydCut/utility_data/word2vec_scb_orchid.pkl
BoydCut/utility_data/wordidx_scb_orchid.csv
BoydCut-1.0.0.dist-info/LICENCE
BoydCut-1.0.0.dist-info/METADATA
BoydCut-1.0.0.dist-info/WHEEL
BoydCut-1.0.0.dist-info/top_level.txt
BoydCut-1.0.0.dist-info/RECORD
