Metadata-Version: 2.1
Name: BoydCut
Version: 1.0.0
Summary: Thai Sentence Segmenter
Home-page: https://github.com/BigDataRPG/BoydCut
Author: Sorratat Sirirattanajakarin
Author-email: sorratat.sirirattanajakarin@gmail.com
License: UNKNOWN
Download-URL: https://github.com/BigDataRPG/BoydCut/archive/v_1.0.0.tar.gz
Keywords: NLP,THAI,SENTENCE
Platform: UNKNOWN
Classifier: Natural Language :: Thai
Classifier: Programming Language :: Python :: 3.6
Classifier: License :: OSI Approved :: MIT License
Classifier: Operating System :: OS Independent
Requires-Python: >=3.6
Requires-Dist: numpy
Requires-Dist: pandas
Requires-Dist: tensorflow
Requires-Dist: deepcut
Requires-Dist: pythainlp
